imca_tools/__init__.py
imca_tools/main.py
imca_tools/command/__init__.py
imca_tools/command/base_var.py
imca_tools/command/find_sub.py
imca_tools/command/list_pkg.py
imca_tools/command/pkg.py
imca_tools/command/workspace.py
imca_tools/command/yame_build.py
imca_tools/logger/__init__.py
imca_tools/logger/logger.py
imca_tools/raw_file/__init__.py
imca_tools/raw_file/build_raw.py
imca_tools/raw_file/clang_format_raw.py
imca_tools/raw_file/clang_raw.py
imca_tools/raw_file/extensions_raw.py
imca_tools/raw_file/help_raw.py
imca_tools/raw_file/impl_inc_raw.py
imca_tools/raw_file/impl_src_raw.py
imca_tools/raw_file/main_raw.py
imca_tools/raw_file/pkg_cmake_raw.py
imca_tools/raw_file/pkg_inc_raw.py
imca_tools/raw_file/pkg_src_raw.py
imca_tools/raw_file/vsc_raw.py
imca_tools/raw_file/workspace_cmake_raw.py
imca_tools/raw_file/workspace_py_raw.py
pyimca-0.1.4.dist-info/LICENSE
pyimca-0.1.4.dist-info/METADATA
pyimca-0.1.4.dist-info/WHEEL
pyimca-0.1.4.dist-info/entry_points.txt
pyimca-0.1.4.dist-info/top_level.txt
pyimca-0.1.4.dist-info/RECORD
