Metadata-Version: 2.1
Name: pyimca
Version: 0.1.4
Summary: 为工程创建一个统一的架构
Home-page: https://github.com/Thrent33/IMCA_FRAME.git
Author: Thrent
Author-email: eel39@yahoo.com
License: GNU General Public License v3.0
Platform: Linux
Classifier: Intended Audience :: Developers
Classifier: Operating System :: OS Independent
Classifier: Natural Language :: Chinese (Simplified)
Classifier: Programming Language :: Python :: 3.7
Classifier: Programming Language :: Python :: 3.8
Classifier: Topic :: Software Development :: Libraries
License-File: LICENSE
Requires-Dist: pyyaml (<=5.3.1)
Requires-Dist: fire
